[
  {
    "platform":"rappi",
    "address_id":"polanco",
    "address_name":"Polanco",
    "address_type":"premium",
    "product_id":"big_mac",
    "product_name":"Big Mac",
    "restaurant":"McDonald's",
    "product_price":152.66,
    "delivery_fee":26.55,
    "service_fee":22.9,
    "total_price":202.11,
    "delivery_time_min":22.0,
    "delivery_time_max":40.0,
    "delivery_time_avg":31.0,
    "discount_text":null,
    "available":true,
    "scrape_timestamp":"2026-03-27T14:16:31.574890+00:00"
  },
  {
    "platform":"ubereats",
    "address_id":"polanco",
    "address_name":"Polanco",
    "address_type":"premium",
    "product_id":"big_mac",
    "product_name":"Big Mac",
    "restaurant":"McDonald's",
    "product_price":141.23,
    "delivery_fee":19.22,
    "service_fee":16.95,
    "total_price":177.4,
    "delivery_time_min":18.0,
    "delivery_time_max":36.0,
    "delivery_time_avg":27.0,
    "discount_text":null,
    "available":true,
    "scrape_timestamp":"2026-03-27T14:16:31.574890+00:00"
  },
  {
    "platform":"didifood",
    "address_id":"polanco",
    "address_name":"Polanco",
    "address_type":"premium",
    "product_id":"big_mac",
    "product_name":"Big Mac",
    "restaurant":"McDonald's",
    "product_price":132.88,
    "delivery_fee":21.09,
    "service_fee":13.29,
    "total_price":167.26,
    "delivery_time_min":27.0,
    "delivery_time_max":45.0,
    "delivery_time_avg":36.0,
    "discount_text":"-20%",
    "available":true,
    "scrape_timestamp":"2026-03-27T14:16:31.574890+00:00"
  },
  {
    "platform":"rappi",
    "address_id":"polanco",
    "address_name":"Polanco",
    "address_type":"premium",
    "product_id":"combo_mediano",
    "product_name":"McCombo Mediano Big Mac",
    "restaurant":"McDonald's",
    "product_price":176.67,
    "delivery_fee":36.94,
    "service_fee":26.5,
    "total_price":240.11,
    "delivery_time_min":22.0,
    "delivery_time_max":40.0,
    "delivery_time_avg":31.0,
    "discount_text":null,
    "available":true,
    "scrape_timestamp":"2026-03-27T14:16:31.574890+00:00"
  },
  {
    "platform":"ubereats",
    "address_id":"polanco",
    "address_name":"Polanco",
    "address_type":"premium",
    "product_id":"combo_mediano",
    "product_name":"McCombo Mediano Big Mac",
    "restaurant":"McDonald's",
    "product_price":175.02,
    "delivery_fee":18.3,
    "service_fee":21.0,
    "total_price":214.32,
    "delivery_time_min":18.0,
    "delivery_time_max":36.0,
    "delivery_time_avg":27.0,
    "discount_text":null,
    "available":true,
    "scrape_timestamp":"2026-03-27T14:16:31.574890+00:00"
  },
  {
    "platform":"didifood",
    "address_id":"polanco",
    "address_name":"Polanco",
    "address_type":"premium",
    "product_id":"combo_mediano",
    "product_name":"McCombo Mediano Big Mac",
    "restaurant":"McDonald's",
    "product_price":null,
    "delivery_fee":null,
    "service_fee":null,
    "total_price":null,
    "delivery_time_min":null,
    "delivery_time_max":null,
    "delivery_time_avg":null,
    "discount_text":null,
    "available":false,
    "scrape_timestamp":"2026-03-27T14:16:31.574890+00:00"
  },
  {
    "platform":"rappi",
    "address_id":"polanco",
    "address_name":"Polanco",
    "address_type":"premium",
    "product_id":"nuggets_10",
    "product_name":"McNuggets 10 piezas",
    "restaurant":"McDonald's",
    "product_price":159.37,
    "delivery_fee":41.75,
    "service_fee":23.91,
    "total_price":225.03,
    "delivery_time_min":22.0,
    "delivery_time_max":40.0,
    "delivery_time_avg":31.0,
    "discount_text":null,
    "available":true,
    "scrape_timestamp":"2026-03-27T14:16:31.574890+00:00"
  },
  {
    "platform":"ubereats",
    "address_id":"polanco",
    "address_name":"Polanco",
    "address_type":"premium",
    "product_id":"nuggets_10",
    "product_name":"McNuggets 10 piezas",
    "restaurant":"McDonald's",
    "product_price":150.6,
    "delivery_fee":11.03,
    "service_fee":18.07,
    "total_price":179.7,
    "delivery_time_min":18.0,
    "delivery_time_max":36.0,
    "delivery_time_avg":27.0,
    "discount_text":null,
    "available":true,
    "scrape_timestamp":"2026-03-27T14:16:31.574890+00:00"
  },
  {
    "platform":"didifood",
    "address_id":"polanco",
    "address_name":"Polanco",
    "address_type":"premium",
    "product_id":"nuggets_10",
    "product_name":"McNuggets 10 piezas",
    "restaurant":"McDonald's",
    "product_price":null,
    "delivery_fee":null,
    "service_fee":null,
    "total_price":null,
    "delivery_time_min":null,
    "delivery_time_max":null,
    "delivery_time_avg":null,
    "discount_text":null,
    "available":false,
    "scrape_timestamp":"2026-03-27T14:16:31.574890+00:00"
  },
  {
    "platform":"rappi",
    "address_id":"polanco",
    "address_name":"Polanco",
    "address_type":"premium",
    "product_id":"coca_600",
    "product_name":"Coca-Cola 600ml",
    "restaurant":"McDonald's",
    "product_price":69.97,
    "delivery_fee":27.94,
    "service_fee":10.5,
    "total_price":108.41,
    "delivery_time_min":22.0,
    "delivery_time_max":40.0,
    "delivery_time_avg":31.0,
    "discount_text":null,
    "available":true,
    "scrape_timestamp":"2026-03-27T14:16:31.574890+00:00"
  },
  {
    "platform":"ubereats",
    "address_id":"polanco",
    "address_name":"Polanco",
    "address_type":"premium",
    "product_id":"coca_600",
    "product_name":"Coca-Cola 600ml",
    "restaurant":"McDonald's",
    "product_price":62.59,
    "delivery_fee":8.98,
    "service_fee":7.51,
    "total_price":79.08,
    "delivery_time_min":18.0,
    "delivery_time_max":36.0,
    "delivery_time_avg":27.0,
    "discount_text":null,
    "available":true,
    "scrape_timestamp":"2026-03-27T14:16:31.574890+00:00"
  },
  {
    "platform":"didifood",
    "address_id":"polanco",
    "address_name":"Polanco",
    "address_type":"premium",
    "product_id":"coca_600",
    "product_name":"Coca-Cola 600ml",
    "restaurant":"McDonald's",
    "product_price":null,
    "delivery_fee":null,
    "service_fee":null,
    "total_price":null,
    "delivery_time_min":null,
    "delivery_time_max":null,
    "delivery_time_avg":null,
    "discount_text":null,
    "available":false,
    "scrape_timestamp":"2026-03-27T14:16:31.574890+00:00"
  },
  {
    "platform":"rappi",
    "address_id":"polanco",
    "address_name":"Polanco",
    "address_type":"premium",
    "product_id":"agua_1l",
    "product_name":"Agua 1L",
    "restaurant":"McDonald's",
    "product_price":41.57,
    "delivery_fee":28.35,
    "service_fee":6.24,
    "total_price":76.16,
    "delivery_time_min":22.0,
    "delivery_time_max":40.0,
    "delivery_time_avg":31.0,
    "discount_text":null,
    "available":true,
    "scrape_timestamp":"2026-03-27T14:16:31.574890+00:00"
  },
  {
    "platform":"ubereats",
    "address_id":"polanco",
    "address_name":"Polanco",
    "address_type":"premium",
    "product_id":"agua_1l",
    "product_name":"Agua 1L",
    "restaurant":"McDonald's",
    "product_price":35.79,
    "delivery_fee":7.65,
    "service_fee":4.29,
    "total_price":47.73,
    "delivery_time_min":18.0,
    "delivery_time_max":36.0,
    "delivery_time_avg":27.0,
    "discount_text":null,
    "available":true,
    "scrape_timestamp":"2026-03-27T14:16:31.574890+00:00"
  },
  {
    "platform":"didifood",
    "address_id":"polanco",
    "address_name":"Polanco",
    "address_type":"premium",
    "product_id":"agua_1l",
    "product_name":"Agua 1L",
    "restaurant":"McDonald's",
    "product_price":36.69,
    "delivery_fee":16.96,
    "service_fee":3.67,
    "total_price":57.32,
    "delivery_time_min":27.0,
    "delivery_time_max":45.0,
    "delivery_time_avg":36.0,
    "discount_text":"-20%",
    "available":true,
    "scrape_timestamp":"2026-03-27T14:16:31.574890+00:00"
  },
  {
    "platform":"rappi",
    "address_id":"condesa",
    "address_name":"Condesa",
    "address_type":"premium",
    "product_id":"big_mac",
    "product_name":"Big Mac",
    "restaurant":"McDonald's",
    "product_price":154.07,
    "delivery_fee":43.83,
    "service_fee":23.11,
    "total_price":221.01,
    "delivery_time_min":22.0,
    "delivery_time_max":40.0,
    "delivery_time_avg":31.0,
    "discount_text":null,
    "available":true,
    "scrape_timestamp":"2026-03-27T14:16:31.574890+00:00"
  },
  {
    "platform":"ubereats",
    "address_id":"condesa",
    "address_name":"Condesa",
    "address_type":"premium",
    "product_id":"big_mac",
    "product_name":"Big Mac",
    "restaurant":"McDonald's",
    "product_price":147.66,
    "delivery_fee":9.92,
    "service_fee":17.72,
    "total_price":175.3,
    "delivery_time_min":18.0,
    "delivery_time_max":36.0,
    "delivery_time_avg":27.0,
    "discount_text":null,
    "available":true,
    "scrape_timestamp":"2026-03-27T14:16:31.574890+00:00"
  },
  {
    "platform":"didifood",
    "address_id":"condesa",
    "address_name":"Condesa",
    "address_type":"premium",
    "product_id":"big_mac",
    "product_name":"Big Mac",
    "restaurant":"McDonald's",
    "product_price":133.6,
    "delivery_fee":19.89,
    "service_fee":13.36,
    "total_price":166.85,
    "delivery_time_min":27.0,
    "delivery_time_max":45.0,
    "delivery_time_avg":36.0,
    "discount_text":null,
    "available":true,
    "scrape_timestamp":"2026-03-27T14:16:31.574890+00:00"
  },
  {
    "platform":"rappi",
    "address_id":"condesa",
    "address_name":"Condesa",
    "address_type":"premium",
    "product_id":"combo_mediano",
    "product_name":"McCombo Mediano Big Mac",
    "restaurant":"McDonald's",
    "product_price":183.57,
    "delivery_fee":38.4,
    "service_fee":27.54,
    "total_price":249.51,
    "delivery_time_min":22.0,
    "delivery_time_max":40.0,
    "delivery_time_avg":31.0,
    "discount_text":"-20%",
    "available":true,
    "scrape_timestamp":"2026-03-27T14:16:31.574890+00:00"
  },
  {
    "platform":"ubereats",
    "address_id":"condesa",
    "address_name":"Condesa",
    "address_type":"premium",
    "product_id":"combo_mediano",
    "product_name":"McCombo Mediano Big Mac",
    "restaurant":"McDonald's",
    "product_price":172.48,
    "delivery_fee":6.39,
    "service_fee":20.7,
    "total_price":199.57,
    "delivery_time_min":18.0,
    "delivery_time_max":36.0,
    "delivery_time_avg":27.0,
    "discount_text":null,
    "available":true,
    "scrape_timestamp":"2026-03-27T14:16:31.574890+00:00"
  },
  {
    "platform":"didifood",
    "address_id":"condesa",
    "address_name":"Condesa",
    "address_type":"premium",
    "product_id":"combo_mediano",
    "product_name":"McCombo Mediano Big Mac",
    "restaurant":"McDonald's",
    "product_price":null,
    "delivery_fee":null,
    "service_fee":null,
    "total_price":null,
    "delivery_time_min":null,
    "delivery_time_max":null,
    "delivery_time_avg":null,
    "discount_text":null,
    "available":false,
    "scrape_timestamp":"2026-03-27T14:16:31.574890+00:00"
  },
  {
    "platform":"rappi",
    "address_id":"condesa",
    "address_name":"Condesa",
    "address_type":"premium",
    "product_id":"nuggets_10",
    "product_name":"McNuggets 10 piezas",
    "restaurant":"McDonald's",
    "product_price":166.17,
    "delivery_fee":38.49,
    "service_fee":24.93,
    "total_price":229.59,
    "delivery_time_min":22.0,
    "delivery_time_max":40.0,
    "delivery_time_avg":31.0,
    "discount_text":null,
    "available":true,
    "scrape_timestamp":"2026-03-27T14:16:31.574890+00:00"
  },
  {
    "platform":"ubereats",
    "address_id":"condesa",
    "address_name":"Condesa",
    "address_type":"premium",
    "product_id":"nuggets_10",
    "product_name":"McNuggets 10 piezas",
    "restaurant":"McDonald's",
    "product_price":152.24,
    "delivery_fee":20.05,
    "service_fee":18.27,
    "total_price":190.56,
    "delivery_time_min":18.0,
    "delivery_time_max":36.0,
    "delivery_time_avg":27.0,
    "discount_text":"2x1",
    "available":true,
    "scrape_timestamp":"2026-03-27T14:16:31.574890+00:00"
  },
  {
    "platform":"didifood",
    "address_id":"condesa",
    "address_name":"Condesa",
    "address_type":"premium",
    "product_id":"nuggets_10",
    "product_name":"McNuggets 10 piezas",
    "restaurant":"McDonald's",
    "product_price":145.36,
    "delivery_fee":14.69,
    "service_fee":14.54,
    "total_price":174.59,
    "delivery_time_min":27.0,
    "delivery_time_max":45.0,
    "delivery_time_avg":36.0,
    "discount_text":null,
    "available":true,
    "scrape_timestamp":"2026-03-27T14:16:31.574890+00:00"
  },
  {
    "platform":"rappi",
    "address_id":"condesa",
    "address_name":"Condesa",
    "address_type":"premium",
    "product_id":"coca_600",
    "product_name":"Coca-Cola 600ml",
    "restaurant":"McDonald's",
    "product_price":67.91,
    "delivery_fee":39.02,
    "service_fee":10.19,
    "total_price":117.12,
    "delivery_time_min":22.0,
    "delivery_time_max":40.0,
    "delivery_time_avg":31.0,
    "discount_text":null,
    "available":true,
    "scrape_timestamp":"2026-03-27T14:16:31.574890+00:00"
  },
  {
    "platform":"ubereats",
    "address_id":"condesa",
    "address_name":"Condesa",
    "address_type":"premium",
    "product_id":"coca_600",
    "product_name":"Coca-Cola 600ml",
    "restaurant":"McDonald's",
    "product_price":63.99,
    "delivery_fee":23.09,
    "service_fee":7.68,
    "total_price":94.76,
    "delivery_time_min":18.0,
    "delivery_time_max":36.0,
    "delivery_time_avg":27.0,
    "discount_text":null,
    "available":true,
    "scrape_timestamp":"2026-03-27T14:16:31.574890+00:00"
  },
  {
    "platform":"didifood",
    "address_id":"condesa",
    "address_name":"Condesa",
    "address_type":"premium",
    "product_id":"coca_600",
    "product_name":"Coca-Cola 600ml",
    "restaurant":"McDonald's",
    "product_price":null,
    "delivery_fee":null,
    "service_fee":null,
    "total_price":null,
    "delivery_time_min":null,
    "delivery_time_max":null,
    "delivery_time_avg":null,
    "discount_text":null,
    "available":false,
    "scrape_timestamp":"2026-03-27T14:16:31.574890+00:00"
  },
  {
    "platform":"rappi",
    "address_id":"condesa",
    "address_name":"Condesa",
    "address_type":"premium",
    "product_id":"agua_1l",
    "product_name":"Agua 1L",
    "restaurant":"McDonald's",
    "product_price":38.22,
    "delivery_fee":39.51,
    "service_fee":5.73,
    "total_price":83.46,
    "delivery_time_min":22.0,
    "delivery_time_max":40.0,
    "delivery_time_avg":31.0,
    "discount_text":null,
    "available":true,
    "scrape_timestamp":"2026-03-27T14:16:31.574890+00:00"
  },
  {
    "platform":"ubereats",
    "address_id":"condesa",
    "address_name":"Condesa",
    "address_type":"premium",
    "product_id":"agua_1l",
    "product_name":"Agua 1L",
    "restaurant":"McDonald's",
    "product_price":42.47,
    "delivery_fee":11.18,
    "service_fee":5.1,
    "total_price":58.75,
    "delivery_time_min":18.0,
    "delivery_time_max":36.0,
    "delivery_time_avg":27.0,
    "discount_text":null,
    "available":true,
    "scrape_timestamp":"2026-03-27T14:16:31.574890+00:00"
  },
  {
    "platform":"didifood",
    "address_id":"condesa",
    "address_name":"Condesa",
    "address_type":"premium",
    "product_id":"agua_1l",
    "product_name":"Agua 1L",
    "restaurant":"McDonald's",
    "product_price":null,
    "delivery_fee":null,
    "service_fee":null,
    "total_price":null,
    "delivery_time_min":null,
    "delivery_time_max":null,
    "delivery_time_avg":null,
    "discount_text":null,
    "available":false,
    "scrape_timestamp":"2026-03-27T14:16:31.574890+00:00"
  },
  {
    "platform":"rappi",
    "address_id":"roma_norte",
    "address_name":"Roma Norte",
    "address_type":"premium",
    "product_id":"big_mac",
    "product_name":"Big Mac",
    "restaurant":"McDonald's",
    "product_price":156.42,
    "delivery_fee":28.59,
    "service_fee":23.46,
    "total_price":208.47,
    "delivery_time_min":22.0,
    "delivery_time_max":40.0,
    "delivery_time_avg":31.0,
    "discount_text":null,
    "available":true,
    "scrape_timestamp":"2026-03-27T14:16:31.574890+00:00"
  },
  {
    "platform":"ubereats",
    "address_id":"roma_norte",
    "address_name":"Roma Norte",
    "address_type":"premium",
    "product_id":"big_mac",
    "product_name":"Big Mac",
    "restaurant":"McDonald's",
    "product_price":146.56,
    "delivery_fee":22.47,
    "service_fee":17.59,
    "total_price":186.62,
    "delivery_time_min":18.0,
    "delivery_time_max":36.0,
    "delivery_time_avg":27.0,
    "discount_text":"-20%",
    "available":true,
    "scrape_timestamp":"2026-03-27T14:16:31.574890+00:00"
  },
  {
    "platform":"didifood",
    "address_id":"roma_norte",
    "address_name":"Roma Norte",
    "address_type":"premium",
    "product_id":"big_mac",
    "product_name":"Big Mac",
    "restaurant":"McDonald's",
    "product_price":136.06,
    "delivery_fee":14.64,
    "service_fee":13.61,
    "total_price":164.31,
    "delivery_time_min":27.0,
    "delivery_time_max":45.0,
    "delivery_time_avg":36.0,
    "discount_text":null,
    "available":true,
    "scrape_timestamp":"2026-03-27T14:16:31.574890+00:00"
  },
  {
    "platform":"rappi",
    "address_id":"roma_norte",
    "address_name":"Roma Norte",
    "address_type":"premium",
    "product_id":"combo_mediano",
    "product_name":"McCombo Mediano Big Mac",
    "restaurant":"McDonald's",
    "product_price":187.89,
    "delivery_fee":35.62,
    "service_fee":28.18,
    "total_price":251.69,
    "delivery_time_min":22.0,
    "delivery_time_max":40.0,
    "delivery_time_avg":31.0,
    "discount_text":null,
    "available":true,
    "scrape_timestamp":"2026-03-27T14:16:31.574890+00:00"
  },
  {
    "platform":"ubereats",
    "address_id":"roma_norte",
    "address_name":"Roma Norte",
    "address_type":"premium",
    "product_id":"combo_mediano",
    "product_name":"McCombo Mediano Big Mac",
    "restaurant":"McDonald's",
    "product_price":177.05,
    "delivery_fee":0.3,
    "service_fee":21.25,
    "total_price":198.6,
    "delivery_time_min":18.0,
    "delivery_time_max":36.0,
    "delivery_time_avg":27.0,
    "discount_text":null,
    "available":true,
    "scrape_timestamp":"2026-03-27T14:16:31.574890+00:00"
  },
  {
    "platform":"didifood",
    "address_id":"roma_norte",
    "address_name":"Roma Norte",
    "address_type":"premium",
    "product_id":"combo_mediano",
    "product_name":"McCombo Mediano Big Mac",
    "restaurant":"McDonald's",
    "product_price":163.89,
    "delivery_fee":18.3,
    "service_fee":16.39,
    "total_price":198.58,
    "delivery_time_min":27.0,
    "delivery_time_max":45.0,
    "delivery_time_avg":36.0,
    "discount_text":null,
    "available":true,
    "scrape_timestamp":"2026-03-27T14:16:31.574890+00:00"
  },
  {
    "platform":"rappi",
    "address_id":"roma_norte",
    "address_name":"Roma Norte",
    "address_type":"premium",
    "product_id":"nuggets_10",
    "product_name":"McNuggets 10 piezas",
    "restaurant":"McDonald's",
    "product_price":157.62,
    "delivery_fee":33.93,
    "service_fee":23.64,
    "total_price":215.19,
    "delivery_time_min":22.0,
    "delivery_time_max":40.0,
    "delivery_time_avg":31.0,
    "discount_text":null,
    "available":true,
    "scrape_timestamp":"2026-03-27T14:16:31.574890+00:00"
  },
  {
    "platform":"ubereats",
    "address_id":"roma_norte",
    "address_name":"Roma Norte",
    "address_type":"premium",
    "product_id":"nuggets_10",
    "product_name":"McNuggets 10 piezas",
    "restaurant":"McDonald's",
    "product_price":158.54,
    "delivery_fee":22.86,
    "service_fee":19.02,
    "total_price":200.42,
    "delivery_time_min":18.0,
    "delivery_time_max":36.0,
    "delivery_time_avg":27.0,
    "discount_text":null,
    "available":true,
    "scrape_timestamp":"2026-03-27T14:16:31.574890+00:00"
  },
  {
    "platform":"didifood",
    "address_id":"roma_norte",
    "address_name":"Roma Norte",
    "address_type":"premium",
    "product_id":"nuggets_10",
    "product_name":"McNuggets 10 piezas",
    "restaurant":"McDonald's",
    "product_price":null,
    "delivery_fee":null,
    "service_fee":null,
    "total_price":null,
    "delivery_time_min":null,
    "delivery_time_max":null,
    "delivery_time_avg":null,
    "discount_text":null,
    "available":false,
    "scrape_timestamp":"2026-03-27T14:16:31.574890+00:00"
  },
  {
    "platform":"rappi",
    "address_id":"roma_norte",
    "address_name":"Roma Norte",
    "address_type":"premium",
    "product_id":"coca_600",
    "product_name":"Coca-Cola 600ml",
    "restaurant":"McDonald's",
    "product_price":63.83,
    "delivery_fee":42.53,
    "service_fee":9.57,
    "total_price":115.93,
    "delivery_time_min":22.0,
    "delivery_time_max":40.0,
    "delivery_time_avg":31.0,
    "discount_text":null,
    "available":true,
    "scrape_timestamp":"2026-03-27T14:16:31.574890+00:00"
  },
  {
    "platform":"ubereats",
    "address_id":"roma_norte",
    "address_name":"Roma Norte",
    "address_type":"premium",
    "product_id":"coca_600",
    "product_name":"Coca-Cola 600ml",
    "restaurant":"McDonald's",
    "product_price":61.98,
    "delivery_fee":16.68,
    "service_fee":7.44,
    "total_price":86.1,
    "delivery_time_min":18.0,
    "delivery_time_max":36.0,
    "delivery_time_avg":27.0,
    "discount_text":null,
    "available":true,
    "scrape_timestamp":"2026-03-27T14:16:31.574890+00:00"
  },
  {
    "platform":"didifood",
    "address_id":"roma_norte",
    "address_name":"Roma Norte",
    "address_type":"premium",
    "product_id":"coca_600",
    "product_name":"Coca-Cola 600ml",
    "restaurant":"McDonald's",
    "product_price":null,
    "delivery_fee":null,
    "service_fee":null,
    "total_price":null,
    "delivery_time_min":null,
    "delivery_time_max":null,
    "delivery_time_avg":null,
    "discount_text":null,
    "available":false,
    "scrape_timestamp":"2026-03-27T14:16:31.574890+00:00"
  },
  {
    "platform":"rappi",
    "address_id":"roma_norte",
    "address_name":"Roma Norte",
    "address_type":"premium",
    "product_id":"agua_1l",
    "product_name":"Agua 1L",
    "restaurant":"McDonald's",
    "product_price":44.76,
    "delivery_fee":35.81,
    "service_fee":6.71,
    "total_price":87.28,
    "delivery_time_min":22.0,
    "delivery_time_max":40.0,
    "delivery_time_avg":31.0,
    "discount_text":null,
    "available":true,
    "scrape_timestamp":"2026-03-27T14:16:31.574890+00:00"
  },
  {
    "platform":"ubereats",
    "address_id":"roma_norte",
    "address_name":"Roma Norte",
    "address_type":"premium",
    "product_id":"agua_1l",
    "product_name":"Agua 1L",
    "restaurant":"McDonald's",
    "product_price":40.3,
    "delivery_fee":0.01,
    "service_fee":4.84,
    "total_price":45.15,
    "delivery_time_min":18.0,
    "delivery_time_max":36.0,
    "delivery_time_avg":27.0,
    "discount_text":null,
    "available":true,
    "scrape_timestamp":"2026-03-27T14:16:31.574890+00:00"
  },
  {
    "platform":"didifood",
    "address_id":"roma_norte",
    "address_name":"Roma Norte",
    "address_type":"premium",
    "product_id":"agua_1l",
    "product_name":"Agua 1L",
    "restaurant":"McDonald's",
    "product_price":null,
    "delivery_fee":null,
    "service_fee":null,
    "total_price":null,
    "delivery_time_min":null,
    "delivery_time_max":null,
    "delivery_time_avg":null,
    "discount_text":null,
    "available":false,
    "scrape_timestamp":"2026-03-27T14:16:31.574890+00:00"
  },
  {
    "platform":"rappi",
    "address_id":"del_valle",
    "address_name":"Del Valle",
    "address_type":"media",
    "product_id":"big_mac",
    "product_name":"Big Mac",
    "restaurant":"McDonald's",
    "product_price":155.71,
    "delivery_fee":46.57,
    "service_fee":23.36,
    "total_price":225.64,
    "delivery_time_min":25.0,
    "delivery_time_max":45.0,
    "delivery_time_avg":35.0,
    "discount_text":null,
    "available":true,
    "scrape_timestamp":"2026-03-27T14:16:31.574890+00:00"
  },
  {
    "platform":"ubereats",
    "address_id":"del_valle",
    "address_name":"Del Valle",
    "address_type":"media",
    "product_id":"big_mac",
    "product_name":"Big Mac",
    "restaurant":"McDonald's",
    "product_price":142.08,
    "delivery_fee":1.68,
    "service_fee":17.05,
    "total_price":160.81,
    "delivery_time_min":20.0,
    "delivery_time_max":40.0,
    "delivery_time_avg":30.0,
    "discount_text":null,
    "available":true,
    "scrape_timestamp":"2026-03-27T14:16:31.574890+00:00"
  },
  {
    "platform":"didifood",
    "address_id":"del_valle",
    "address_name":"Del Valle",
    "address_type":"media",
    "product_id":"big_mac",
    "product_name":"Big Mac",
    "restaurant":"McDonald's",
    "product_price":132.86,
    "delivery_fee":24.72,
    "service_fee":13.29,
    "total_price":170.87,
    "delivery_time_min":30.0,
    "delivery_time_max":50.0,
    "delivery_time_avg":40.0,
    "discount_text":"-20%",
    "available":true,
    "scrape_timestamp":"2026-03-27T14:16:31.574890+00:00"
  },
  {
    "platform":"rappi",
    "address_id":"del_valle",
    "address_name":"Del Valle",
    "address_type":"media",
    "product_id":"combo_mediano",
    "product_name":"McCombo Mediano Big Mac",
    "restaurant":"McDonald's",
    "product_price":175.14,
    "delivery_fee":38.51,
    "service_fee":26.27,
    "total_price":239.92,
    "delivery_time_min":25.0,
    "delivery_time_max":45.0,
    "delivery_time_avg":35.0,
    "discount_text":null,
    "available":true,
    "scrape_timestamp":"2026-03-27T14:16:31.574890+00:00"
  },
  {
    "platform":"ubereats",
    "address_id":"del_valle",
    "address_name":"Del Valle",
    "address_type":"media",
    "product_id":"combo_mediano",
    "product_name":"McCombo Mediano Big Mac",
    "restaurant":"McDonald's",
    "product_price":168.71,
    "delivery_fee":25.3,
    "service_fee":20.25,
    "total_price":214.26,
    "delivery_time_min":20.0,
    "delivery_time_max":40.0,
    "delivery_time_avg":30.0,
    "discount_text":null,
    "available":true,
    "scrape_timestamp":"2026-03-27T14:16:31.574890+00:00"
  },
  {
    "platform":"didifood",
    "address_id":"del_valle",
    "address_name":"Del Valle",
    "address_type":"media",
    "product_id":"combo_mediano",
    "product_name":"McCombo Mediano Big Mac",
    "restaurant":"McDonald's",
    "product_price":null,
    "delivery_fee":null,
    "service_fee":null,
    "total_price":null,
    "delivery_time_min":null,
    "delivery_time_max":null,
    "delivery_time_avg":null,
    "discount_text":null,
    "available":false,
    "scrape_timestamp":"2026-03-27T14:16:31.574890+00:00"
  },
  {
    "platform":"rappi",
    "address_id":"del_valle",
    "address_name":"Del Valle",
    "address_type":"media",
    "product_id":"nuggets_10",
    "product_name":"McNuggets 10 piezas",
    "restaurant":"McDonald's",
    "product_price":162.11,
    "delivery_fee":43.6,
    "service_fee":24.32,
    "total_price":230.03,
    "delivery_time_min":25.0,
    "delivery_time_max":45.0,
    "delivery_time_avg":35.0,
    "discount_text":null,
    "available":true,
    "scrape_timestamp":"2026-03-27T14:16:31.574890+00:00"
  },
  {
    "platform":"ubereats",
    "address_id":"del_valle",
    "address_name":"Del Valle",
    "address_type":"media",
    "product_id":"nuggets_10",
    "product_name":"McNuggets 10 piezas",
    "restaurant":"McDonald's",
    "product_price":152.12,
    "delivery_fee":28.86,
    "service_fee":18.25,
    "total_price":199.23,
    "delivery_time_min":20.0,
    "delivery_time_max":40.0,
    "delivery_time_avg":30.0,
    "discount_text":null,
    "available":true,
    "scrape_timestamp":"2026-03-27T14:16:31.574890+00:00"
  },
  {
    "platform":"didifood",
    "address_id":"del_valle",
    "address_name":"Del Valle",
    "address_type":"media",
    "product_id":"nuggets_10",
    "product_name":"McNuggets 10 piezas",
    "restaurant":"McDonald's",
    "product_price":null,
    "delivery_fee":null,
    "service_fee":null,
    "total_price":null,
    "delivery_time_min":null,
    "delivery_time_max":null,
    "delivery_time_avg":null,
    "discount_text":null,
    "available":false,
    "scrape_timestamp":"2026-03-27T14:16:31.574890+00:00"
  },
  {
    "platform":"rappi",
    "address_id":"del_valle",
    "address_name":"Del Valle",
    "address_type":"media",
    "product_id":"coca_600",
    "product_name":"Coca-Cola 600ml",
    "restaurant":"McDonald's",
    "product_price":67.38,
    "delivery_fee":31.42,
    "service_fee":10.11,
    "total_price":108.91,
    "delivery_time_min":25.0,
    "delivery_time_max":45.0,
    "delivery_time_avg":35.0,
    "discount_text":null,
    "available":true,
    "scrape_timestamp":"2026-03-27T14:16:31.574890+00:00"
  },
  {
    "platform":"ubereats",
    "address_id":"del_valle",
    "address_name":"Del Valle",
    "address_type":"media",
    "product_id":"coca_600",
    "product_name":"Coca-Cola 600ml",
    "restaurant":"McDonald's",
    "product_price":62.38,
    "delivery_fee":17.06,
    "service_fee":7.49,
    "total_price":86.93,
    "delivery_time_min":20.0,
    "delivery_time_max":40.0,
    "delivery_time_avg":30.0,
    "discount_text":null,
    "available":true,
    "scrape_timestamp":"2026-03-27T14:16:31.574890+00:00"
  },
  {
    "platform":"didifood",
    "address_id":"del_valle",
    "address_name":"Del Valle",
    "address_type":"media",
    "product_id":"coca_600",
    "product_name":"Coca-Cola 600ml",
    "restaurant":"McDonald's",
    "product_price":null,
    "delivery_fee":null,
    "service_fee":null,
    "total_price":null,
    "delivery_time_min":null,
    "delivery_time_max":null,
    "delivery_time_avg":null,
    "discount_text":null,
    "available":false,
    "scrape_timestamp":"2026-03-27T14:16:31.574890+00:00"
  },
  {
    "platform":"rappi",
    "address_id":"del_valle",
    "address_name":"Del Valle",
    "address_type":"media",
    "product_id":"agua_1l",
    "product_name":"Agua 1L",
    "restaurant":"McDonald's",
    "product_price":37.5,
    "delivery_fee":41.62,
    "service_fee":5.62,
    "total_price":84.74,
    "delivery_time_min":25.0,
    "delivery_time_max":45.0,
    "delivery_time_avg":35.0,
    "discount_text":null,
    "available":true,
    "scrape_timestamp":"2026-03-27T14:16:31.574890+00:00"
  },
  {
    "platform":"ubereats",
    "address_id":"del_valle",
    "address_name":"Del Valle",
    "address_type":"media",
    "product_id":"agua_1l",
    "product_name":"Agua 1L",
    "restaurant":"McDonald's",
    "product_price":44.05,
    "delivery_fee":24.93,
    "service_fee":5.29,
    "total_price":74.27,
    "delivery_time_min":20.0,
    "delivery_time_max":40.0,
    "delivery_time_avg":30.0,
    "discount_text":"-20%",
    "available":true,
    "scrape_timestamp":"2026-03-27T14:16:31.574890+00:00"
  },
  {
    "platform":"didifood",
    "address_id":"del_valle",
    "address_name":"Del Valle",
    "address_type":"media",
    "product_id":"agua_1l",
    "product_name":"Agua 1L",
    "restaurant":"McDonald's",
    "product_price":null,
    "delivery_fee":null,
    "service_fee":null,
    "total_price":null,
    "delivery_time_min":null,
    "delivery_time_max":null,
    "delivery_time_avg":null,
    "discount_text":null,
    "available":false,
    "scrape_timestamp":"2026-03-27T14:16:31.574890+00:00"
  },
  {
    "platform":"rappi",
    "address_id":"coyoacan",
    "address_name":"Coyoacán",
    "address_type":"media",
    "product_id":"big_mac",
    "product_name":"Big Mac",
    "restaurant":"McDonald's",
    "product_price":151.05,
    "delivery_fee":39.78,
    "service_fee":22.66,
    "total_price":213.49,
    "delivery_time_min":25.0,
    "delivery_time_max":45.0,
    "delivery_time_avg":35.0,
    "discount_text":null,
    "available":true,
    "scrape_timestamp":"2026-03-27T14:16:31.574890+00:00"
  },
  {
    "platform":"ubereats",
    "address_id":"coyoacan",
    "address_name":"Coyoacán",
    "address_type":"media",
    "product_id":"big_mac",
    "product_name":"Big Mac",
    "restaurant":"McDonald's",
    "product_price":147.82,
    "delivery_fee":16.71,
    "service_fee":17.74,
    "total_price":182.27,
    "delivery_time_min":20.0,
    "delivery_time_max":40.0,
    "delivery_time_avg":30.0,
    "discount_text":null,
    "available":true,
    "scrape_timestamp":"2026-03-27T14:16:31.574890+00:00"
  },
  {
    "platform":"didifood",
    "address_id":"coyoacan",
    "address_name":"Coyoacán",
    "address_type":"media",
    "product_id":"big_mac",
    "product_name":"Big Mac",
    "restaurant":"McDonald's",
    "product_price":null,
    "delivery_fee":null,
    "service_fee":null,
    "total_price":null,
    "delivery_time_min":null,
    "delivery_time_max":null,
    "delivery_time_avg":null,
    "discount_text":null,
    "available":false,
    "scrape_timestamp":"2026-03-27T14:16:31.574890+00:00"
  },
  {
    "platform":"rappi",
    "address_id":"coyoacan",
    "address_name":"Coyoacán",
    "address_type":"media",
    "product_id":"combo_mediano",
    "product_name":"McCombo Mediano Big Mac",
    "restaurant":"McDonald's",
    "product_price":179.23,
    "delivery_fee":30.89,
    "service_fee":26.88,
    "total_price":237.0,
    "delivery_time_min":25.0,
    "delivery_time_max":45.0,
    "delivery_time_avg":35.0,
    "discount_text":null,
    "available":true,
    "scrape_timestamp":"2026-03-27T14:16:31.574890+00:00"
  },
  {
    "platform":"ubereats",
    "address_id":"coyoacan",
    "address_name":"Coyoacán",
    "address_type":"media",
    "product_id":"combo_mediano",
    "product_name":"McCombo Mediano Big Mac",
    "restaurant":"McDonald's",
    "product_price":169.96,
    "delivery_fee":11.92,
    "service_fee":20.4,
    "total_price":202.28,
    "delivery_time_min":20.0,
    "delivery_time_max":40.0,
    "delivery_time_avg":30.0,
    "discount_text":null,
    "available":true,
    "scrape_timestamp":"2026-03-27T14:16:31.574890+00:00"
  },
  {
    "platform":"didifood",
    "address_id":"coyoacan",
    "address_name":"Coyoacán",
    "address_type":"media",
    "product_id":"combo_mediano",
    "product_name":"McCombo Mediano Big Mac",
    "restaurant":"McDonald's",
    "product_price":null,
    "delivery_fee":null,
    "service_fee":null,
    "total_price":null,
    "delivery_time_min":null,
    "delivery_time_max":null,
    "delivery_time_avg":null,
    "discount_text":null,
    "available":false,
    "scrape_timestamp":"2026-03-27T14:16:31.574890+00:00"
  },
  {
    "platform":"rappi",
    "address_id":"coyoacan",
    "address_name":"Coyoacán",
    "address_type":"media",
    "product_id":"nuggets_10",
    "product_name":"McNuggets 10 piezas",
    "restaurant":"McDonald's",
    "product_price":163.31,
    "delivery_fee":41.92,
    "service_fee":24.5,
    "total_price":229.73,
    "delivery_time_min":25.0,
    "delivery_time_max":45.0,
    "delivery_time_avg":35.0,
    "discount_text":"Envío gratis",
    "available":true,
    "scrape_timestamp":"2026-03-27T14:16:31.574890+00:00"
  },
  {
    "platform":"ubereats",
    "address_id":"coyoacan",
    "address_name":"Coyoacán",
    "address_type":"media",
    "product_id":"nuggets_10",
    "product_name":"McNuggets 10 piezas",
    "restaurant":"McDonald's",
    "product_price":157.01,
    "delivery_fee":3.17,
    "service_fee":18.84,
    "total_price":179.02,
    "delivery_time_min":20.0,
    "delivery_time_max":40.0,
    "delivery_time_avg":30.0,
    "discount_text":"-$30",
    "available":true,
    "scrape_timestamp":"2026-03-27T14:16:31.574890+00:00"
  },
  {
    "platform":"didifood",
    "address_id":"coyoacan",
    "address_name":"Coyoacán",
    "address_type":"media",
    "product_id":"nuggets_10",
    "product_name":"McNuggets 10 piezas",
    "restaurant":"McDonald's",
    "product_price":null,
    "delivery_fee":null,
    "service_fee":null,
    "total_price":null,
    "delivery_time_min":null,
    "delivery_time_max":null,
    "delivery_time_avg":null,
    "discount_text":null,
    "available":false,
    "scrape_timestamp":"2026-03-27T14:16:31.574890+00:00"
  },
  {
    "platform":"rappi",
    "address_id":"coyoacan",
    "address_name":"Coyoacán",
    "address_type":"media",
    "product_id":"coca_600",
    "product_name":"Coca-Cola 600ml",
    "restaurant":"McDonald's",
    "product_price":63.88,
    "delivery_fee":38.25,
    "service_fee":9.58,
    "total_price":111.71,
    "delivery_time_min":25.0,
    "delivery_time_max":45.0,
    "delivery_time_avg":35.0,
    "discount_text":null,
    "available":true,
    "scrape_timestamp":"2026-03-27T14:16:31.574890+00:00"
  },
  {
    "platform":"ubereats",
    "address_id":"coyoacan",
    "address_name":"Coyoacán",
    "address_type":"media",
    "product_id":"coca_600",
    "product_name":"Coca-Cola 600ml",
    "restaurant":"McDonald's",
    "product_price":59.75,
    "delivery_fee":23.43,
    "service_fee":7.17,
    "total_price":90.35,
    "delivery_time_min":20.0,
    "delivery_time_max":40.0,
    "delivery_time_avg":30.0,
    "discount_text":null,
    "available":true,
    "scrape_timestamp":"2026-03-27T14:16:31.574890+00:00"
  },
  {
    "platform":"didifood",
    "address_id":"coyoacan",
    "address_name":"Coyoacán",
    "address_type":"media",
    "product_id":"coca_600",
    "product_name":"Coca-Cola 600ml",
    "restaurant":"McDonald's",
    "product_price":null,
    "delivery_fee":null,
    "service_fee":null,
    "total_price":null,
    "delivery_time_min":null,
    "delivery_time_max":null,
    "delivery_time_avg":null,
    "discount_text":null,
    "available":false,
    "scrape_timestamp":"2026-03-27T14:16:31.574890+00:00"
  },
  {
    "platform":"rappi",
    "address_id":"coyoacan",
    "address_name":"Coyoacán",
    "address_type":"media",
    "product_id":"agua_1l",
    "product_name":"Agua 1L",
    "restaurant":"McDonald's",
    "product_price":43.6,
    "delivery_fee":39.81,
    "service_fee":6.54,
    "total_price":89.95,
    "delivery_time_min":25.0,
    "delivery_time_max":45.0,
    "delivery_time_avg":35.0,
    "discount_text":"2x1",
    "available":true,
    "scrape_timestamp":"2026-03-27T14:16:31.574890+00:00"
  },
  {
    "platform":"ubereats",
    "address_id":"coyoacan",
    "address_name":"Coyoacán",
    "address_type":"media",
    "product_id":"agua_1l",
    "product_name":"Agua 1L",
    "restaurant":"McDonald's",
    "product_price":44.26,
    "delivery_fee":24.61,
    "service_fee":5.31,
    "total_price":74.18,
    "delivery_time_min":20.0,
    "delivery_time_max":40.0,
    "delivery_time_avg":30.0,
    "discount_text":"-$30",
    "available":true,
    "scrape_timestamp":"2026-03-27T14:16:31.574890+00:00"
  },
  {
    "platform":"didifood",
    "address_id":"coyoacan",
    "address_name":"Coyoacán",
    "address_type":"media",
    "product_id":"agua_1l",
    "product_name":"Agua 1L",
    "restaurant":"McDonald's",
    "product_price":null,
    "delivery_fee":null,
    "service_fee":null,
    "total_price":null,
    "delivery_time_min":null,
    "delivery_time_max":null,
    "delivery_time_avg":null,
    "discount_text":null,
    "available":false,
    "scrape_timestamp":"2026-03-27T14:16:31.574890+00:00"
  },
  {
    "platform":"rappi",
    "address_id":"santa_fe",
    "address_name":"Santa Fe",
    "address_type":"media",
    "product_id":"big_mac",
    "product_name":"Big Mac",
    "restaurant":"McDonald's",
    "product_price":155.03,
    "delivery_fee":47.05,
    "service_fee":23.25,
    "total_price":225.33,
    "delivery_time_min":25.0,
    "delivery_time_max":45.0,
    "delivery_time_avg":35.0,
    "discount_text":"2x1",
    "available":true,
    "scrape_timestamp":"2026-03-27T14:16:31.574890+00:00"
  },
  {
    "platform":"ubereats",
    "address_id":"santa_fe",
    "address_name":"Santa Fe",
    "address_type":"media",
    "product_id":"big_mac",
    "product_name":"Big Mac",
    "restaurant":"McDonald's",
    "product_price":148.85,
    "delivery_fee":7.69,
    "service_fee":17.86,
    "total_price":174.4,
    "delivery_time_min":20.0,
    "delivery_time_max":40.0,
    "delivery_time_avg":30.0,
    "discount_text":null,
    "available":true,
    "scrape_timestamp":"2026-03-27T14:16:31.574890+00:00"
  },
  {
    "platform":"didifood",
    "address_id":"santa_fe",
    "address_name":"Santa Fe",
    "address_type":"media",
    "product_id":"big_mac",
    "product_name":"Big Mac",
    "restaurant":"McDonald's",
    "product_price":null,
    "delivery_fee":null,
    "service_fee":null,
    "total_price":null,
    "delivery_time_min":null,
    "delivery_time_max":null,
    "delivery_time_avg":null,
    "discount_text":null,
    "available":false,
    "scrape_timestamp":"2026-03-27T14:16:31.574890+00:00"
  },
  {
    "platform":"rappi",
    "address_id":"santa_fe",
    "address_name":"Santa Fe",
    "address_type":"media",
    "product_id":"combo_mediano",
    "product_name":"McCombo Mediano Big Mac",
    "restaurant":"McDonald's",
    "product_price":179.47,
    "delivery_fee":48.15,
    "service_fee":26.92,
    "total_price":254.54,
    "delivery_time_min":25.0,
    "delivery_time_max":45.0,
    "delivery_time_avg":35.0,
    "discount_text":null,
    "available":true,
    "scrape_timestamp":"2026-03-27T14:16:31.574890+00:00"
  },
  {
    "platform":"ubereats",
    "address_id":"santa_fe",
    "address_name":"Santa Fe",
    "address_type":"media",
    "product_id":"combo_mediano",
    "product_name":"McCombo Mediano Big Mac",
    "restaurant":"McDonald's",
    "product_price":172.78,
    "delivery_fee":20.83,
    "service_fee":20.73,
    "total_price":214.34,
    "delivery_time_min":20.0,
    "delivery_time_max":40.0,
    "delivery_time_avg":30.0,
    "discount_text":"Envío gratis",
    "available":true,
    "scrape_timestamp":"2026-03-27T14:16:31.574890+00:00"
  },
  {
    "platform":"didifood",
    "address_id":"santa_fe",
    "address_name":"Santa Fe",
    "address_type":"media",
    "product_id":"combo_mediano",
    "product_name":"McCombo Mediano Big Mac",
    "restaurant":"McDonald's",
    "product_price":null,
    "delivery_fee":null,
    "service_fee":null,
    "total_price":null,
    "delivery_time_min":null,
    "delivery_time_max":null,
    "delivery_time_avg":null,
    "discount_text":null,
    "available":false,
    "scrape_timestamp":"2026-03-27T14:16:31.574890+00:00"
  },
  {
    "platform":"rappi",
    "address_id":"santa_fe",
    "address_name":"Santa Fe",
    "address_type":"media",
    "product_id":"nuggets_10",
    "product_name":"McNuggets 10 piezas",
    "restaurant":"McDonald's",
    "product_price":157.06,
    "delivery_fee":43.71,
    "service_fee":23.56,
    "total_price":224.33,
    "delivery_time_min":25.0,
    "delivery_time_max":45.0,
    "delivery_time_avg":35.0,
    "discount_text":"Envío gratis",
    "available":true,
    "scrape_timestamp":"2026-03-27T14:16:31.574890+00:00"
  },
  {
    "platform":"ubereats",
    "address_id":"santa_fe",
    "address_name":"Santa Fe",
    "address_type":"media",
    "product_id":"nuggets_10",
    "product_name":"McNuggets 10 piezas",
    "restaurant":"McDonald's",
    "product_price":149.57,
    "delivery_fee":16.94,
    "service_fee":17.95,
    "total_price":184.46,
    "delivery_time_min":20.0,
    "delivery_time_max":40.0,
    "delivery_time_avg":30.0,
    "discount_text":null,
    "available":true,
    "scrape_timestamp":"2026-03-27T14:16:31.574890+00:00"
  },
  {
    "platform":"didifood",
    "address_id":"santa_fe",
    "address_name":"Santa Fe",
    "address_type":"media",
    "product_id":"nuggets_10",
    "product_name":"McNuggets 10 piezas",
    "restaurant":"McDonald's",
    "product_price":143.05,
    "delivery_fee":34.22,
    "service_fee":14.31,
    "total_price":191.58,
    "delivery_time_min":30.0,
    "delivery_time_max":50.0,
    "delivery_time_avg":40.0,
    "discount_text":"-20%",
    "available":true,
    "scrape_timestamp":"2026-03-27T14:16:31.574890+00:00"
  },
  {
    "platform":"rappi",
    "address_id":"santa_fe",
    "address_name":"Santa Fe",
    "address_type":"media",
    "product_id":"coca_600",
    "product_name":"Coca-Cola 600ml",
    "restaurant":"McDonald's",
    "product_price":62.67,
    "delivery_fee":30.36,
    "service_fee":9.4,
    "total_price":102.43,
    "delivery_time_min":25.0,
    "delivery_time_max":45.0,
    "delivery_time_avg":35.0,
    "discount_text":null,
    "available":true,
    "scrape_timestamp":"2026-03-27T14:16:31.574890+00:00"
  },
  {
    "platform":"ubereats",
    "address_id":"santa_fe",
    "address_name":"Santa Fe",
    "address_type":"media",
    "product_id":"coca_600",
    "product_name":"Coca-Cola 600ml",
    "restaurant":"McDonald's",
    "product_price":63.04,
    "delivery_fee":27.31,
    "service_fee":7.56,
    "total_price":97.91,
    "delivery_time_min":20.0,
    "delivery_time_max":40.0,
    "delivery_time_avg":30.0,
    "discount_text":null,
    "available":true,
    "scrape_timestamp":"2026-03-27T14:16:31.574890+00:00"
  },
  {
    "platform":"didifood",
    "address_id":"santa_fe",
    "address_name":"Santa Fe",
    "address_type":"media",
    "product_id":"coca_600",
    "product_name":"Coca-Cola 600ml",
    "restaurant":"McDonald's",
    "product_price":null,
    "delivery_fee":null,
    "service_fee":null,
    "total_price":null,
    "delivery_time_min":null,
    "delivery_time_max":null,
    "delivery_time_avg":null,
    "discount_text":null,
    "available":false,
    "scrape_timestamp":"2026-03-27T14:16:31.574890+00:00"
  },
  {
    "platform":"rappi",
    "address_id":"santa_fe",
    "address_name":"Santa Fe",
    "address_type":"media",
    "product_id":"agua_1l",
    "product_name":"Agua 1L",
    "restaurant":"McDonald's",
    "product_price":37.17,
    "delivery_fee":30.64,
    "service_fee":5.58,
    "total_price":73.39,
    "delivery_time_min":25.0,
    "delivery_time_max":45.0,
    "delivery_time_avg":35.0,
    "discount_text":null,
    "available":true,
    "scrape_timestamp":"2026-03-27T14:16:31.574890+00:00"
  },
  {
    "platform":"ubereats",
    "address_id":"santa_fe",
    "address_name":"Santa Fe",
    "address_type":"media",
    "product_id":"agua_1l",
    "product_name":"Agua 1L",
    "restaurant":"McDonald's",
    "product_price":40.65,
    "delivery_fee":9.17,
    "service_fee":4.88,
    "total_price":54.7,
    "delivery_time_min":20.0,
    "delivery_time_max":40.0,
    "delivery_time_avg":30.0,
    "discount_text":null,
    "available":true,
    "scrape_timestamp":"2026-03-27T14:16:31.574890+00:00"
  },
  {
    "platform":"didifood",
    "address_id":"santa_fe",
    "address_name":"Santa Fe",
    "address_type":"media",
    "product_id":"agua_1l",
    "product_name":"Agua 1L",
    "restaurant":"McDonald's",
    "product_price":36.23,
    "delivery_fee":20.31,
    "service_fee":3.62,
    "total_price":60.16,
    "delivery_time_min":30.0,
    "delivery_time_max":50.0,
    "delivery_time_avg":40.0,
    "discount_text":"Envío gratis",
    "available":true,
    "scrape_timestamp":"2026-03-27T14:16:31.574890+00:00"
  },
  {
    "platform":"rappi",
    "address_id":"tlalpan",
    "address_name":"Tlalpan",
    "address_type":"media",
    "product_id":"big_mac",
    "product_name":"Big Mac",
    "restaurant":"McDonald's",
    "product_price":150.75,
    "delivery_fee":47.58,
    "service_fee":22.61,
    "total_price":220.94,
    "delivery_time_min":25.0,
    "delivery_time_max":45.0,
    "delivery_time_avg":35.0,
    "discount_text":null,
    "available":true,
    "scrape_timestamp":"2026-03-27T14:16:31.574890+00:00"
  },
  {
    "platform":"ubereats",
    "address_id":"tlalpan",
    "address_name":"Tlalpan",
    "address_type":"media",
    "product_id":"big_mac",
    "product_name":"Big Mac",
    "restaurant":"McDonald's",
    "product_price":139.09,
    "delivery_fee":18.01,
    "service_fee":16.69,
    "total_price":173.79,
    "delivery_time_min":20.0,
    "delivery_time_max":40.0,
    "delivery_time_avg":30.0,
    "discount_text":null,
    "available":true,
    "scrape_timestamp":"2026-03-27T14:16:31.574890+00:00"
  },
  {
    "platform":"didifood",
    "address_id":"tlalpan",
    "address_name":"Tlalpan",
    "address_type":"media",
    "product_id":"big_mac",
    "product_name":"Big Mac",
    "restaurant":"McDonald's",
    "product_price":null,
    "delivery_fee":null,
    "service_fee":null,
    "total_price":null,
    "delivery_time_min":null,
    "delivery_time_max":null,
    "delivery_time_avg":null,
    "discount_text":null,
    "available":false,
    "scrape_timestamp":"2026-03-27T14:16:31.574890+00:00"
  },
  {
    "platform":"rappi",
    "address_id":"tlalpan",
    "address_name":"Tlalpan",
    "address_type":"media",
    "product_id":"combo_mediano",
    "product_name":"McCombo Mediano Big Mac",
    "restaurant":"McDonald's",
    "product_price":181.15,
    "delivery_fee":39.12,
    "service_fee":27.17,
    "total_price":247.44,
    "delivery_time_min":25.0,
    "delivery_time_max":45.0,
    "delivery_time_avg":35.0,
    "discount_text":"Envío gratis",
    "available":true,
    "scrape_timestamp":"2026-03-27T14:16:31.574890+00:00"
  },
  {
    "platform":"ubereats",
    "address_id":"tlalpan",
    "address_name":"Tlalpan",
    "address_type":"media",
    "product_id":"combo_mediano",
    "product_name":"McCombo Mediano Big Mac",
    "restaurant":"McDonald's",
    "product_price":177.33,
    "delivery_fee":25.5,
    "service_fee":21.28,
    "total_price":224.11,
    "delivery_time_min":20.0,
    "delivery_time_max":40.0,
    "delivery_time_avg":30.0,
    "discount_text":null,
    "available":true,
    "scrape_timestamp":"2026-03-27T14:16:31.574890+00:00"
  },
  {
    "platform":"didifood",
    "address_id":"tlalpan",
    "address_name":"Tlalpan",
    "address_type":"media",
    "product_id":"combo_mediano",
    "product_name":"McCombo Mediano Big Mac",
    "restaurant":"McDonald's",
    "product_price":null,
    "delivery_fee":null,
    "service_fee":null,
    "total_price":null,
    "delivery_time_min":null,
    "delivery_time_max":null,
    "delivery_time_avg":null,
    "discount_text":null,
    "available":false,
    "scrape_timestamp":"2026-03-27T14:16:31.574890+00:00"
  },
  {
    "platform":"rappi",
    "address_id":"tlalpan",
    "address_name":"Tlalpan",
    "address_type":"media",
    "product_id":"nuggets_10",
    "product_name":"McNuggets 10 piezas",
    "restaurant":"McDonald's",
    "product_price":165.2,
    "delivery_fee":43.07,
    "service_fee":24.78,
    "total_price":233.05,
    "delivery_time_min":25.0,
    "delivery_time_max":45.0,
    "delivery_time_avg":35.0,
    "discount_text":null,
    "available":true,
    "scrape_timestamp":"2026-03-27T14:16:31.574890+00:00"
  },
  {
    "platform":"ubereats",
    "address_id":"tlalpan",
    "address_name":"Tlalpan",
    "address_type":"media",
    "product_id":"nuggets_10",
    "product_name":"McNuggets 10 piezas",
    "restaurant":"McDonald's",
    "product_price":158.87,
    "delivery_fee":18.97,
    "service_fee":19.06,
    "total_price":196.9,
    "delivery_time_min":20.0,
    "delivery_time_max":40.0,
    "delivery_time_avg":30.0,
    "discount_text":"Envío gratis",
    "available":true,
    "scrape_timestamp":"2026-03-27T14:16:31.574890+00:00"
  },
  {
    "platform":"didifood",
    "address_id":"tlalpan",
    "address_name":"Tlalpan",
    "address_type":"media",
    "product_id":"nuggets_10",
    "product_name":"McNuggets 10 piezas",
    "restaurant":"McDonald's",
    "product_price":142.53,
    "delivery_fee":32.56,
    "service_fee":14.25,
    "total_price":189.34,
    "delivery_time_min":30.0,
    "delivery_time_max":50.0,
    "delivery_time_avg":40.0,
    "discount_text":null,
    "available":true,
    "scrape_timestamp":"2026-03-27T14:16:31.574890+00:00"
  },
  {
    "platform":"rappi",
    "address_id":"tlalpan",
    "address_name":"Tlalpan",
    "address_type":"media",
    "product_id":"coca_600",
    "product_name":"Coca-Cola 600ml",
    "restaurant":"McDonald's",
    "product_price":71.29,
    "delivery_fee":43.85,
    "service_fee":10.69,
    "total_price":125.83,
    "delivery_time_min":25.0,
    "delivery_time_max":45.0,
    "delivery_time_avg":35.0,
    "discount_text":"Envío gratis",
    "available":true,
    "scrape_timestamp":"2026-03-27T14:16:31.574890+00:00"
  },
  {
    "platform":"ubereats",
    "address_id":"tlalpan",
    "address_name":"Tlalpan",
    "address_type":"media",
    "product_id":"coca_600",
    "product_name":"Coca-Cola 600ml",
    "restaurant":"McDonald's",
    "product_price":65.05,
    "delivery_fee":20.81,
    "service_fee":7.81,
    "total_price":93.67,
    "delivery_time_min":20.0,
    "delivery_time_max":40.0,
    "delivery_time_avg":30.0,
    "discount_text":null,
    "available":true,
    "scrape_timestamp":"2026-03-27T14:16:31.574890+00:00"
  },
  {
    "platform":"didifood",
    "address_id":"tlalpan",
    "address_name":"Tlalpan",
    "address_type":"media",
    "product_id":"coca_600",
    "product_name":"Coca-Cola 600ml",
    "restaurant":"McDonald's",
    "product_price":58.56,
    "delivery_fee":24.77,
    "service_fee":5.86,
    "total_price":89.19,
    "delivery_time_min":30.0,
    "delivery_time_max":50.0,
    "delivery_time_avg":40.0,
    "discount_text":null,
    "available":true,
    "scrape_timestamp":"2026-03-27T14:16:31.574890+00:00"
  },
  {
    "platform":"rappi",
    "address_id":"tlalpan",
    "address_name":"Tlalpan",
    "address_type":"media",
    "product_id":"agua_1l",
    "product_name":"Agua 1L",
    "restaurant":"McDonald's",
    "product_price":45.63,
    "delivery_fee":30.85,
    "service_fee":6.84,
    "total_price":83.32,
    "delivery_time_min":25.0,
    "delivery_time_max":45.0,
    "delivery_time_avg":35.0,
    "discount_text":null,
    "available":true,
    "scrape_timestamp":"2026-03-27T14:16:31.574890+00:00"
  },
  {
    "platform":"ubereats",
    "address_id":"tlalpan",
    "address_name":"Tlalpan",
    "address_type":"media",
    "product_id":"agua_1l",
    "product_name":"Agua 1L",
    "restaurant":"McDonald's",
    "product_price":37.77,
    "delivery_fee":0.1,
    "service_fee":4.53,
    "total_price":42.4,
    "delivery_time_min":20.0,
    "delivery_time_max":40.0,
    "delivery_time_avg":30.0,
    "discount_text":null,
    "available":true,
    "scrape_timestamp":"2026-03-27T14:16:31.574890+00:00"
  },
  {
    "platform":"didifood",
    "address_id":"tlalpan",
    "address_name":"Tlalpan",
    "address_type":"media",
    "product_id":"agua_1l",
    "product_name":"Agua 1L",
    "restaurant":"McDonald's",
    "product_price":35.74,
    "delivery_fee":29.82,
    "service_fee":3.57,
    "total_price":69.13,
    "delivery_time_min":30.0,
    "delivery_time_max":50.0,
    "delivery_time_avg":40.0,
    "discount_text":null,
    "available":true,
    "scrape_timestamp":"2026-03-27T14:16:31.574890+00:00"
  },
  {
    "platform":"rappi",
    "address_id":"iztapalapa",
    "address_name":"Iztapalapa",
    "address_type":"popular",
    "product_id":"big_mac",
    "product_name":"Big Mac",
    "restaurant":"McDonald's",
    "product_price":150.44,
    "delivery_fee":37.95,
    "service_fee":22.57,
    "total_price":210.96,
    "delivery_time_min":32.0,
    "delivery_time_max":58.0,
    "delivery_time_avg":45.0,
    "discount_text":"-20%",
    "available":true,
    "scrape_timestamp":"2026-03-27T14:16:31.574890+00:00"
  },
  {
    "platform":"ubereats",
    "address_id":"iztapalapa",
    "address_name":"Iztapalapa",
    "address_type":"popular",
    "product_id":"big_mac",
    "product_name":"Big Mac",
    "restaurant":"McDonald's",
    "product_price":144.46,
    "delivery_fee":31.46,
    "service_fee":17.34,
    "total_price":193.26,
    "delivery_time_min":26.0,
    "delivery_time_max":52.0,
    "delivery_time_avg":39.0,
    "discount_text":null,
    "available":true,
    "scrape_timestamp":"2026-03-27T14:16:31.574890+00:00"
  },
  {
    "platform":"didifood",
    "address_id":"iztapalapa",
    "address_name":"Iztapalapa",
    "address_type":"popular",
    "product_id":"big_mac",
    "product_name":"Big Mac",
    "restaurant":"McDonald's",
    "product_price":null,
    "delivery_fee":null,
    "service_fee":null,
    "total_price":null,
    "delivery_time_min":null,
    "delivery_time_max":null,
    "delivery_time_avg":null,
    "discount_text":null,
    "available":false,
    "scrape_timestamp":"2026-03-27T14:16:31.574890+00:00"
  },
  {
    "platform":"rappi",
    "address_id":"iztapalapa",
    "address_name":"Iztapalapa",
    "address_type":"popular",
    "product_id":"combo_mediano",
    "product_name":"McCombo Mediano Big Mac",
    "restaurant":"McDonald's",
    "product_price":175.12,
    "delivery_fee":45.71,
    "service_fee":26.27,
    "total_price":247.1,
    "delivery_time_min":32.0,
    "delivery_time_max":58.0,
    "delivery_time_avg":45.0,
    "discount_text":null,
    "available":true,
    "scrape_timestamp":"2026-03-27T14:16:31.574890+00:00"
  },
  {
    "platform":"ubereats",
    "address_id":"iztapalapa",
    "address_name":"Iztapalapa",
    "address_type":"popular",
    "product_id":"combo_mediano",
    "product_name":"McCombo Mediano Big Mac",
    "restaurant":"McDonald's",
    "product_price":176.15,
    "delivery_fee":32.45,
    "service_fee":21.14,
    "total_price":229.74,
    "delivery_time_min":26.0,
    "delivery_time_max":52.0,
    "delivery_time_avg":39.0,
    "discount_text":null,
    "available":true,
    "scrape_timestamp":"2026-03-27T14:16:31.574890+00:00"
  },
  {
    "platform":"didifood",
    "address_id":"iztapalapa",
    "address_name":"Iztapalapa",
    "address_type":"popular",
    "product_id":"combo_mediano",
    "product_name":"McCombo Mediano Big Mac",
    "restaurant":"McDonald's",
    "product_price":null,
    "delivery_fee":null,
    "service_fee":null,
    "total_price":null,
    "delivery_time_min":null,
    "delivery_time_max":null,
    "delivery_time_avg":null,
    "discount_text":null,
    "available":false,
    "scrape_timestamp":"2026-03-27T14:16:31.574890+00:00"
  },
  {
    "platform":"rappi",
    "address_id":"iztapalapa",
    "address_name":"Iztapalapa",
    "address_type":"popular",
    "product_id":"nuggets_10",
    "product_name":"McNuggets 10 piezas",
    "restaurant":"McDonald's",
    "product_price":159.07,
    "delivery_fee":40.37,
    "service_fee":23.86,
    "total_price":223.3,
    "delivery_time_min":32.0,
    "delivery_time_max":58.0,
    "delivery_time_avg":45.0,
    "discount_text":null,
    "available":true,
    "scrape_timestamp":"2026-03-27T14:16:31.574890+00:00"
  },
  {
    "platform":"ubereats",
    "address_id":"iztapalapa",
    "address_name":"Iztapalapa",
    "address_type":"popular",
    "product_id":"nuggets_10",
    "product_name":"McNuggets 10 piezas",
    "restaurant":"McDonald's",
    "product_price":157.84,
    "delivery_fee":15.32,
    "service_fee":18.94,
    "total_price":192.1,
    "delivery_time_min":26.0,
    "delivery_time_max":52.0,
    "delivery_time_avg":39.0,
    "discount_text":null,
    "available":true,
    "scrape_timestamp":"2026-03-27T14:16:31.574890+00:00"
  },
  {
    "platform":"didifood",
    "address_id":"iztapalapa",
    "address_name":"Iztapalapa",
    "address_type":"popular",
    "product_id":"nuggets_10",
    "product_name":"McNuggets 10 piezas",
    "restaurant":"McDonald's",
    "product_price":null,
    "delivery_fee":null,
    "service_fee":null,
    "total_price":null,
    "delivery_time_min":null,
    "delivery_time_max":null,
    "delivery_time_avg":null,
    "discount_text":null,
    "available":false,
    "scrape_timestamp":"2026-03-27T14:16:31.574890+00:00"
  },
  {
    "platform":"rappi",
    "address_id":"iztapalapa",
    "address_name":"Iztapalapa",
    "address_type":"popular",
    "product_id":"coca_600",
    "product_name":"Coca-Cola 600ml",
    "restaurant":"McDonald's",
    "product_price":71.71,
    "delivery_fee":60.18,
    "service_fee":10.76,
    "total_price":142.65,
    "delivery_time_min":32.0,
    "delivery_time_max":58.0,
    "delivery_time_avg":45.0,
    "discount_text":null,
    "available":true,
    "scrape_timestamp":"2026-03-27T14:16:31.574890+00:00"
  },
  {
    "platform":"ubereats",
    "address_id":"iztapalapa",
    "address_name":"Iztapalapa",
    "address_type":"popular",
    "product_id":"coca_600",
    "product_name":"Coca-Cola 600ml",
    "restaurant":"McDonald's",
    "product_price":67.11,
    "delivery_fee":33.23,
    "service_fee":8.05,
    "total_price":108.39,
    "delivery_time_min":26.0,
    "delivery_time_max":52.0,
    "delivery_time_avg":39.0,
    "discount_text":"Envío gratis",
    "available":true,
    "scrape_timestamp":"2026-03-27T14:16:31.574890+00:00"
  },
  {
    "platform":"didifood",
    "address_id":"iztapalapa",
    "address_name":"Iztapalapa",
    "address_type":"popular",
    "product_id":"coca_600",
    "product_name":"Coca-Cola 600ml",
    "restaurant":"McDonald's",
    "product_price":59.96,
    "delivery_fee":36.92,
    "service_fee":6.0,
    "total_price":102.88,
    "delivery_time_min":39.0,
    "delivery_time_max":65.0,
    "delivery_time_avg":52.0,
    "discount_text":null,
    "available":true,
    "scrape_timestamp":"2026-03-27T14:16:31.574890+00:00"
  },
  {
    "platform":"rappi",
    "address_id":"iztapalapa",
    "address_name":"Iztapalapa",
    "address_type":"popular",
    "product_id":"agua_1l",
    "product_name":"Agua 1L",
    "restaurant":"McDonald's",
    "product_price":39.36,
    "delivery_fee":41.84,
    "service_fee":5.9,
    "total_price":87.1,
    "delivery_time_min":32.0,
    "delivery_time_max":58.0,
    "delivery_time_avg":45.0,
    "discount_text":null,
    "available":true,
    "scrape_timestamp":"2026-03-27T14:16:31.574890+00:00"
  },
  {
    "platform":"ubereats",
    "address_id":"iztapalapa",
    "address_name":"Iztapalapa",
    "address_type":"popular",
    "product_id":"agua_1l",
    "product_name":"Agua 1L",
    "restaurant":"McDonald's",
    "product_price":38.83,
    "delivery_fee":1.46,
    "service_fee":4.66,
    "total_price":44.95,
    "delivery_time_min":26.0,
    "delivery_time_max":52.0,
    "delivery_time_avg":39.0,
    "discount_text":null,
    "available":true,
    "scrape_timestamp":"2026-03-27T14:16:31.574890+00:00"
  },
  {
    "platform":"didifood",
    "address_id":"iztapalapa",
    "address_name":"Iztapalapa",
    "address_type":"popular",
    "product_id":"agua_1l",
    "product_name":"Agua 1L",
    "restaurant":"McDonald's",
    "product_price":null,
    "delivery_fee":null,
    "service_fee":null,
    "total_price":null,
    "delivery_time_min":null,
    "delivery_time_max":null,
    "delivery_time_avg":null,
    "discount_text":null,
    "available":false,
    "scrape_timestamp":"2026-03-27T14:16:31.574890+00:00"
  },
  {
    "platform":"rappi",
    "address_id":"naucalpan",
    "address_name":"Naucalpan",
    "address_type":"popular",
    "product_id":"big_mac",
    "product_name":"Big Mac",
    "restaurant":"McDonald's",
    "product_price":155.59,
    "delivery_fee":46.79,
    "service_fee":23.34,
    "total_price":225.72,
    "delivery_time_min":32.0,
    "delivery_time_max":58.0,
    "delivery_time_avg":45.0,
    "discount_text":null,
    "available":true,
    "scrape_timestamp":"2026-03-27T14:16:31.574890+00:00"
  },
  {
    "platform":"ubereats",
    "address_id":"naucalpan",
    "address_name":"Naucalpan",
    "address_type":"popular",
    "product_id":"big_mac",
    "product_name":"Big Mac",
    "restaurant":"McDonald's",
    "product_price":147.71,
    "delivery_fee":8.4,
    "service_fee":17.73,
    "total_price":173.84,
    "delivery_time_min":26.0,
    "delivery_time_max":52.0,
    "delivery_time_avg":39.0,
    "discount_text":null,
    "available":true,
    "scrape_timestamp":"2026-03-27T14:16:31.574890+00:00"
  },
  {
    "platform":"didifood",
    "address_id":"naucalpan",
    "address_name":"Naucalpan",
    "address_type":"popular",
    "product_id":"big_mac",
    "product_name":"Big Mac",
    "restaurant":"McDonald's",
    "product_price":null,
    "delivery_fee":null,
    "service_fee":null,
    "total_price":null,
    "delivery_time_min":null,
    "delivery_time_max":null,
    "delivery_time_avg":null,
    "discount_text":null,
    "available":false,
    "scrape_timestamp":"2026-03-27T14:16:31.574890+00:00"
  },
  {
    "platform":"rappi",
    "address_id":"naucalpan",
    "address_name":"Naucalpan",
    "address_type":"popular",
    "product_id":"combo_mediano",
    "product_name":"McCombo Mediano Big Mac",
    "restaurant":"McDonald's",
    "product_price":177.35,
    "delivery_fee":39.5,
    "service_fee":26.6,
    "total_price":243.45,
    "delivery_time_min":32.0,
    "delivery_time_max":58.0,
    "delivery_time_avg":45.0,
    "discount_text":null,
    "available":true,
    "scrape_timestamp":"2026-03-27T14:16:31.574890+00:00"
  },
  {
    "platform":"ubereats",
    "address_id":"naucalpan",
    "address_name":"Naucalpan",
    "address_type":"popular",
    "product_id":"combo_mediano",
    "product_name":"McCombo Mediano Big Mac",
    "restaurant":"McDonald's",
    "product_price":169.92,
    "delivery_fee":19.2,
    "service_fee":20.39,
    "total_price":209.51,
    "delivery_time_min":26.0,
    "delivery_time_max":52.0,
    "delivery_time_avg":39.0,
    "discount_text":null,
    "available":true,
    "scrape_timestamp":"2026-03-27T14:16:31.574890+00:00"
  },
  {
    "platform":"didifood",
    "address_id":"naucalpan",
    "address_name":"Naucalpan",
    "address_type":"popular",
    "product_id":"combo_mediano",
    "product_name":"McCombo Mediano Big Mac",
    "restaurant":"McDonald's",
    "product_price":161.15,
    "delivery_fee":20.22,
    "service_fee":16.12,
    "total_price":197.49,
    "delivery_time_min":39.0,
    "delivery_time_max":65.0,
    "delivery_time_avg":52.0,
    "discount_text":null,
    "available":true,
    "scrape_timestamp":"2026-03-27T14:16:31.574890+00:00"
  },
  {
    "platform":"rappi",
    "address_id":"naucalpan",
    "address_name":"Naucalpan",
    "address_type":"popular",
    "product_id":"nuggets_10",
    "product_name":"McNuggets 10 piezas",
    "restaurant":"McDonald's",
    "product_price":159.19,
    "delivery_fee":52.8,
    "service_fee":23.88,
    "total_price":235.87,
    "delivery_time_min":32.0,
    "delivery_time_max":58.0,
    "delivery_time_avg":45.0,
    "discount_text":null,
    "available":true,
    "scrape_timestamp":"2026-03-27T14:16:31.574890+00:00"
  },
  {
    "platform":"ubereats",
    "address_id":"naucalpan",
    "address_name":"Naucalpan",
    "address_type":"popular",
    "product_id":"nuggets_10",
    "product_name":"McNuggets 10 piezas",
    "restaurant":"McDonald's",
    "product_price":149.38,
    "delivery_fee":22.49,
    "service_fee":17.93,
    "total_price":189.8,
    "delivery_time_min":26.0,
    "delivery_time_max":52.0,
    "delivery_time_avg":39.0,
    "discount_text":null,
    "available":true,
    "scrape_timestamp":"2026-03-27T14:16:31.574890+00:00"
  },
  {
    "platform":"didifood",
    "address_id":"naucalpan",
    "address_name":"Naucalpan",
    "address_type":"popular",
    "product_id":"nuggets_10",
    "product_name":"McNuggets 10 piezas",
    "restaurant":"McDonald's",
    "product_price":145.7,
    "delivery_fee":45.09,
    "service_fee":14.57,
    "total_price":205.36,
    "delivery_time_min":39.0,
    "delivery_time_max":65.0,
    "delivery_time_avg":52.0,
    "discount_text":"-20%",
    "available":true,
    "scrape_timestamp":"2026-03-27T14:16:31.575890+00:00"
  },
  {
    "platform":"rappi",
    "address_id":"naucalpan",
    "address_name":"Naucalpan",
    "address_type":"popular",
    "product_id":"coca_600",
    "product_name":"Coca-Cola 600ml",
    "restaurant":"McDonald's",
    "product_price":64.62,
    "delivery_fee":56.13,
    "service_fee":9.69,
    "total_price":130.44,
    "delivery_time_min":32.0,
    "delivery_time_max":58.0,
    "delivery_time_avg":45.0,
    "discount_text":"-20%",
    "available":true,
    "scrape_timestamp":"2026-03-27T14:16:31.575890+00:00"
  },
  {
    "platform":"ubereats",
    "address_id":"naucalpan",
    "address_name":"Naucalpan",
    "address_type":"popular",
    "product_id":"coca_600",
    "product_name":"Coca-Cola 600ml",
    "restaurant":"McDonald's",
    "product_price":62.64,
    "delivery_fee":2.64,
    "service_fee":7.52,
    "total_price":72.8,
    "delivery_time_min":26.0,
    "delivery_time_max":52.0,
    "delivery_time_avg":39.0,
    "discount_text":null,
    "available":true,
    "scrape_timestamp":"2026-03-27T14:16:31.575890+00:00"
  },
  {
    "platform":"didifood",
    "address_id":"naucalpan",
    "address_name":"Naucalpan",
    "address_type":"popular",
    "product_id":"coca_600",
    "product_name":"Coca-Cola 600ml",
    "restaurant":"McDonald's",
    "product_price":null,
    "delivery_fee":null,
    "service_fee":null,
    "total_price":null,
    "delivery_time_min":null,
    "delivery_time_max":null,
    "delivery_time_avg":null,
    "discount_text":null,
    "available":false,
    "scrape_timestamp":"2026-03-27T14:16:31.575890+00:00"
  },
  {
    "platform":"rappi",
    "address_id":"naucalpan",
    "address_name":"Naucalpan",
    "address_type":"popular",
    "product_id":"agua_1l",
    "product_name":"Agua 1L",
    "restaurant":"McDonald's",
    "product_price":40.05,
    "delivery_fee":59.75,
    "service_fee":6.01,
    "total_price":105.81,
    "delivery_time_min":32.0,
    "delivery_time_max":58.0,
    "delivery_time_avg":45.0,
    "discount_text":null,
    "available":true,
    "scrape_timestamp":"2026-03-27T14:16:31.575890+00:00"
  },
  {
    "platform":"ubereats",
    "address_id":"naucalpan",
    "address_name":"Naucalpan",
    "address_type":"popular",
    "product_id":"agua_1l",
    "product_name":"Agua 1L",
    "restaurant":"McDonald's",
    "product_price":38.0,
    "delivery_fee":11.66,
    "service_fee":4.56,
    "total_price":54.22,
    "delivery_time_min":26.0,
    "delivery_time_max":52.0,
    "delivery_time_avg":39.0,
    "discount_text":null,
    "available":true,
    "scrape_timestamp":"2026-03-27T14:16:31.575890+00:00"
  },
  {
    "platform":"didifood",
    "address_id":"naucalpan",
    "address_name":"Naucalpan",
    "address_type":"popular",
    "product_id":"agua_1l",
    "product_name":"Agua 1L",
    "restaurant":"McDonald's",
    "product_price":null,
    "delivery_fee":null,
    "service_fee":null,
    "total_price":null,
    "delivery_time_min":null,
    "delivery_time_max":null,
    "delivery_time_avg":null,
    "discount_text":null,
    "available":false,
    "scrape_timestamp":"2026-03-27T14:16:31.575890+00:00"
  },
  {
    "platform":"rappi",
    "address_id":"ecatepec",
    "address_name":"Ecatepec",
    "address_type":"popular",
    "product_id":"big_mac",
    "product_name":"Big Mac",
    "restaurant":"McDonald's",
    "product_price":149.05,
    "delivery_fee":41.01,
    "service_fee":22.36,
    "total_price":212.42,
    "delivery_time_min":32.0,
    "delivery_time_max":58.0,
    "delivery_time_avg":45.0,
    "discount_text":null,
    "available":true,
    "scrape_timestamp":"2026-03-27T14:16:31.575890+00:00"
  },
  {
    "platform":"ubereats",
    "address_id":"ecatepec",
    "address_name":"Ecatepec",
    "address_type":"popular",
    "product_id":"big_mac",
    "product_name":"Big Mac",
    "restaurant":"McDonald's",
    "product_price":148.4,
    "delivery_fee":25.53,
    "service_fee":17.81,
    "total_price":191.74,
    "delivery_time_min":26.0,
    "delivery_time_max":52.0,
    "delivery_time_avg":39.0,
    "discount_text":null,
    "available":true,
    "scrape_timestamp":"2026-03-27T14:16:31.575890+00:00"
  },
  {
    "platform":"didifood",
    "address_id":"ecatepec",
    "address_name":"Ecatepec",
    "address_type":"popular",
    "product_id":"big_mac",
    "product_name":"Big Mac",
    "restaurant":"McDonald's",
    "product_price":134.91,
    "delivery_fee":33.75,
    "service_fee":13.49,
    "total_price":182.15,
    "delivery_time_min":39.0,
    "delivery_time_max":65.0,
    "delivery_time_avg":52.0,
    "discount_text":"Envío gratis",
    "available":true,
    "scrape_timestamp":"2026-03-27T14:16:31.575890+00:00"
  },
  {
    "platform":"rappi",
    "address_id":"ecatepec",
    "address_name":"Ecatepec",
    "address_type":"popular",
    "product_id":"combo_mediano",
    "product_name":"McCombo Mediano Big Mac",
    "restaurant":"McDonald's",
    "product_price":176.34,
    "delivery_fee":58.13,
    "service_fee":26.45,
    "total_price":260.92,
    "delivery_time_min":32.0,
    "delivery_time_max":58.0,
    "delivery_time_avg":45.0,
    "discount_text":null,
    "available":true,
    "scrape_timestamp":"2026-03-27T14:16:31.575890+00:00"
  },
  {
    "platform":"ubereats",
    "address_id":"ecatepec",
    "address_name":"Ecatepec",
    "address_type":"popular",
    "product_id":"combo_mediano",
    "product_name":"McCombo Mediano Big Mac",
    "restaurant":"McDonald's",
    "product_price":169.51,
    "delivery_fee":16.66,
    "service_fee":20.34,
    "total_price":206.51,
    "delivery_time_min":26.0,
    "delivery_time_max":52.0,
    "delivery_time_avg":39.0,
    "discount_text":null,
    "available":true,
    "scrape_timestamp":"2026-03-27T14:16:31.575890+00:00"
  },
  {
    "platform":"didifood",
    "address_id":"ecatepec",
    "address_name":"Ecatepec",
    "address_type":"popular",
    "product_id":"combo_mediano",
    "product_name":"McCombo Mediano Big Mac",
    "restaurant":"McDonald's",
    "product_price":null,
    "delivery_fee":null,
    "service_fee":null,
    "total_price":null,
    "delivery_time_min":null,
    "delivery_time_max":null,
    "delivery_time_avg":null,
    "discount_text":null,
    "available":false,
    "scrape_timestamp":"2026-03-27T14:16:31.575890+00:00"
  },
  {
    "platform":"rappi",
    "address_id":"ecatepec",
    "address_name":"Ecatepec",
    "address_type":"popular",
    "product_id":"nuggets_10",
    "product_name":"McNuggets 10 piezas",
    "restaurant":"McDonald's",
    "product_price":164.78,
    "delivery_fee":62.66,
    "service_fee":24.72,
    "total_price":252.16,
    "delivery_time_min":32.0,
    "delivery_time_max":58.0,
    "delivery_time_avg":45.0,
    "discount_text":null,
    "available":true,
    "scrape_timestamp":"2026-03-27T14:16:31.575890+00:00"
  },
  {
    "platform":"ubereats",
    "address_id":"ecatepec",
    "address_name":"Ecatepec",
    "address_type":"popular",
    "product_id":"nuggets_10",
    "product_name":"McNuggets 10 piezas",
    "restaurant":"McDonald's",
    "product_price":155.59,
    "delivery_fee":10.7,
    "service_fee":18.67,
    "total_price":184.96,
    "delivery_time_min":26.0,
    "delivery_time_max":52.0,
    "delivery_time_avg":39.0,
    "discount_text":null,
    "available":true,
    "scrape_timestamp":"2026-03-27T14:16:31.575890+00:00"
  },
  {
    "platform":"didifood",
    "address_id":"ecatepec",
    "address_name":"Ecatepec",
    "address_type":"popular",
    "product_id":"nuggets_10",
    "product_name":"McNuggets 10 piezas",
    "restaurant":"McDonald's",
    "product_price":142.44,
    "delivery_fee":44.25,
    "service_fee":14.24,
    "total_price":200.93,
    "delivery_time_min":39.0,
    "delivery_time_max":65.0,
    "delivery_time_avg":52.0,
    "discount_text":null,
    "available":true,
    "scrape_timestamp":"2026-03-27T14:16:31.575890+00:00"
  },
  {
    "platform":"rappi",
    "address_id":"ecatepec",
    "address_name":"Ecatepec",
    "address_type":"popular",
    "product_id":"coca_600",
    "product_name":"Coca-Cola 600ml",
    "restaurant":"McDonald's",
    "product_price":65.21,
    "delivery_fee":58.67,
    "service_fee":9.78,
    "total_price":133.66,
    "delivery_time_min":32.0,
    "delivery_time_max":58.0,
    "delivery_time_avg":45.0,
    "discount_text":"2x1",
    "available":true,
    "scrape_timestamp":"2026-03-27T14:16:31.575890+00:00"
  },
  {
    "platform":"ubereats",
    "address_id":"ecatepec",
    "address_name":"Ecatepec",
    "address_type":"popular",
    "product_id":"coca_600",
    "product_name":"Coca-Cola 600ml",
    "restaurant":"McDonald's",
    "product_price":61.45,
    "delivery_fee":17.91,
    "service_fee":7.37,
    "total_price":86.73,
    "delivery_time_min":26.0,
    "delivery_time_max":52.0,
    "delivery_time_avg":39.0,
    "discount_text":null,
    "available":true,
    "scrape_timestamp":"2026-03-27T14:16:31.575890+00:00"
  },
  {
    "platform":"didifood",
    "address_id":"ecatepec",
    "address_name":"Ecatepec",
    "address_type":"popular",
    "product_id":"coca_600",
    "product_name":"Coca-Cola 600ml",
    "restaurant":"McDonald's",
    "product_price":null,
    "delivery_fee":null,
    "service_fee":null,
    "total_price":null,
    "delivery_time_min":null,
    "delivery_time_max":null,
    "delivery_time_avg":null,
    "discount_text":null,
    "available":false,
    "scrape_timestamp":"2026-03-27T14:16:31.575890+00:00"
  },
  {
    "platform":"rappi",
    "address_id":"ecatepec",
    "address_name":"Ecatepec",
    "address_type":"popular",
    "product_id":"agua_1l",
    "product_name":"Agua 1L",
    "restaurant":"McDonald's",
    "product_price":41.1,
    "delivery_fee":54.07,
    "service_fee":6.17,
    "total_price":101.34,
    "delivery_time_min":32.0,
    "delivery_time_max":58.0,
    "delivery_time_avg":45.0,
    "discount_text":"-$30",
    "available":true,
    "scrape_timestamp":"2026-03-27T14:16:31.575890+00:00"
  },
  {
    "platform":"ubereats",
    "address_id":"ecatepec",
    "address_name":"Ecatepec",
    "address_type":"popular",
    "product_id":"agua_1l",
    "product_name":"Agua 1L",
    "restaurant":"McDonald's",
    "product_price":39.94,
    "delivery_fee":9.2,
    "service_fee":4.79,
    "total_price":53.93,
    "delivery_time_min":26.0,
    "delivery_time_max":52.0,
    "delivery_time_avg":39.0,
    "discount_text":null,
    "available":true,
    "scrape_timestamp":"2026-03-27T14:16:31.575890+00:00"
  },
  {
    "platform":"didifood",
    "address_id":"ecatepec",
    "address_name":"Ecatepec",
    "address_type":"popular",
    "product_id":"agua_1l",
    "product_name":"Agua 1L",
    "restaurant":"McDonald's",
    "product_price":null,
    "delivery_fee":null,
    "service_fee":null,
    "total_price":null,
    "delivery_time_min":null,
    "delivery_time_max":null,
    "delivery_time_avg":null,
    "discount_text":null,
    "available":false,
    "scrape_timestamp":"2026-03-27T14:16:31.575890+00:00"
  }
]